tgdata/__init__.py
tgdata/connection_engine.py
tgdata/message_engine.py
tgdata/models.py
tgdata/progress.py
tgdata/tgdata.py
tgdata/utils.py
tgdata/smoke_tests/__init__.py
tgdata/smoke_tests/my_test.py
tgdata/smoke_tests/test_00_connection.py
tgdata/smoke_tests/test_01_list_group_chats.py
tgdata/smoke_tests/test_02_get_message_count.py
tgdata/smoke_tests/test_03_get_all_messages.py
tgdata/smoke_tests/test_04_get_all_messages_in_batches.py
tgdata/smoke_tests/test_05_with_progress_feature.py
tgdata/smoke_tests/test_06_polling_simple.py
tgdata/smoke_tests/test_07_on_new_message_simple.py
tgdata/smoke_tests/test_07_real_time_event_handler.py
tgdata/smoke_tests/test_08_batch_callback.py
tgdata/smoke_tests/test_08_polling.py
tgdata/smoke_tests/test_10_advanced_features.py
tgdata/smoke_tests/test_debug_min_id.py
tgdata/smoke_tests/test_polling_debug.py
tgdata-0.0.1.dist-info/METADATA
tgdata-0.0.1.dist-info/WHEEL
tgdata-0.0.1.dist-info/top_level.txt
tgdata-0.0.1.dist-info/RECORD
